util_functions/__init__.py
util_functions/json/__init__.py
util_functions/json/json.py
util_functions/math/__init__.py
util_functions/math/math.py
util_functions-1.0.1.dist-info/METADATA
util_functions-1.0.1.dist-info/WHEEL
util_functions-1.0.1.dist-info/top_level.txt
util_functions-1.0.1.dist-info/RECORD
