Metadata-Version: 2.1
Name: util-functions
Version: 1.0.1
Summary: Repository contains utility functions which perform commonly needed operations 
Author: Patryk Palej
License: UNKNOWN
Platform: UNKNOWN
Requires-Dist: numpy
Requires-Dist: pandas
